jwtauth/__init__.py
jwtauth/admin.py
jwtauth/manager.py
jwtauth/middleware.py
jwtauth/migrations/0001_initial.py
jwtauth/migrations/__init__.py
jwtauth/models.py
jwtauth/settings.py
jwtauth/tokens.py
jwtauth/utils.py
drf_cookie_jwtauth-0.0.8.dist-info/LICENSE
drf_cookie_jwtauth-0.0.8.dist-info/METADATA
drf_cookie_jwtauth-0.0.8.dist-info/WHEEL
drf_cookie_jwtauth-0.0.8.dist-info/RECORD
