Metadata-Version: 2.3
Name: drf-cookie-jwtauth
Version: 0.0.8
Summary: JWT-based authentication for Django REST Framework
License: MIT
Author: LorenzoCelli
Author-email: lorenzo.celli00@gmail.com
Requires-Python: >=3.10,<4.0
Classifier: License :: OSI Approved :: MIT License
Classifier: Programming Language :: Python :: 3
Classifier: Programming Language :: Python :: 3.10
Classifier: Programming Language :: Python :: 3.11
Classifier: Programming Language :: Python :: 3.12
Classifier: Programming Language :: Python :: 3.13
Requires-Dist: Django (>=5.2.3,<6.0.0)
Requires-Dist: PyJWT (>=2.8.0)
Requires-Dist: djangorestframework (>=3.15.2,<4.0.0)
